fcrawler/__init__.py
fcrawler/__main__.py
fcrawler/application.py
fcrawler/utils.py
fcrawler/version.py
fcrawler-1.0.1.dist-info/LICENSE
fcrawler-1.0.1.dist-info/METADATA
fcrawler-1.0.1.dist-info/WHEEL
fcrawler-1.0.1.dist-info/entry_points.txt
fcrawler-1.0.1.dist-info/top_level.txt
fcrawler-1.0.1.dist-info/RECORD
